llgd/__init__.py
llgd/cli/__init__.py
llgd/cli/cli.py
llgd/config/__init__.py
llgd/config/llgd_config.py
llgd/lib/__init__.py
llgd/lib/llgd_lib.py
llgd/ui/__init__.py
llgd/ui/__main__.py
litra_driver-0.0.8.dist-info/COMMITMENT
litra_driver-0.0.8.dist-info/LICENSE
litra_driver-0.0.8.dist-info/METADATA
litra_driver-0.0.8.dist-info/WHEEL
litra_driver-0.0.8.dist-info/entry_points.txt
litra_driver-0.0.8.dist-info/top_level.txt
litra_driver-0.0.8.dist-info/RECORD
