Metadata-Version: 2.1
Name: litra-driver
Version: 0.0.8
Summary: Logitech Lumitra Glow and Beam Driver
Home-page: https://github.com/kharyam/litra-driver
Download-URL: https://github.com/kharyam/litra-driver/archive/v0.0.8.tar.gz
Author: Khary Mendez
Author-email: kharyam+llgd@gmail.com
Keywords: logitech lumitra glow,CLI,UI
Classifier: Programming Language :: Python :: 3.6
Classifier: Programming Language :: Python :: 3.8
Classifier: License :: OSI Approved :: GNU General Public License v3 or later (GPLv3+)
Classifier: Operating System :: OS Independent
Requires-Python: >=3.6
License-File: LICENSE
License-File: COMMITMENT
Requires-Dist: pyusb
Requires-Dist: fire
Requires-Dist: PySimpleGui
Requires-Dist: psgtray
Requires-Dist: pystray
Provides-Extra: tests
Requires-Dist: wheel ; extra == 'tests'
Requires-Dist: pylint ; extra == 'tests'
Requires-Dist: flake8 ; extra == 'tests'
Requires-Dist: bandit ; extra == 'tests'
Requires-Dist: pytest ; extra == 'tests'
Requires-Dist: pytest-cov ; extra == 'tests'
Requires-Dist: testfixtures ; extra == 'tests'
Requires-Dist: mock ; extra == 'tests'
Requires-Dist: codecov ; extra == 'tests'
Requires-Dist: tox ; extra == 'tests'
